MANIFEST.in
README.rst
requirements.txt
setup.cfg
setup.py
datary/__init__.py
datary/version.py
datary.egg-info/PKG-INFO
datary.egg-info/SOURCES.txt
datary.egg-info/dependency_links.txt
datary.egg-info/requires.txt
datary.egg-info/top_level.txt
datary/auth/__init__.py
datary/auth/auth.py
datary/auth/test/__init__.py
datary/auth/test/test_auth.py
datary/categories/__init__.py
datary/categories/categories.py
datary/categories/test/__init__.py
datary/categories/test/test_categories.py
datary/commits/__init__.py
datary/commits/commits.py
datary/commits/test/__init__.py
datary/commits/test/test_commits.py
datary/datasets/__init__.py
datary/datasets/datasets.py
datary/datasets/test/__init__.py
datary/datasets/test/test_datasets.py
datary/members/__init__.py
datary/members/members.py
datary/members/test/__init__.py
datary/members/test/test_members.py
datary/operations/__init__.py
datary/operations/add.py
datary/operations/clean.py
datary/operations/limits.py
datary/operations/modify.py
datary/operations/remove.py
datary/operations/rename.py
datary/operations/test/__init__.py
datary/operations/test/test_add.py
datary/operations/test/test_clean.py
datary/operations/test/test_modify.py
datary/operations/test/test_remove.py
datary/operations/test/test_rename.py
datary/repos/__init__.py
datary/repos/repos.py
datary/repos/test/__init__.py
datary/repos/test/test_repos.py
datary/requests/__init__.py
datary/requests/requests.py
datary/requests/test/__init__.py
datary/requests/test/test_requests.py
datary/test/__init__.py
datary/test/mock_requests.py
datary/test/test_datary.py
datary/workdirs/__init__.py
datary/workdirs/workdirs.py
datary/workdirs/test/__init__.py
datary/workdirs/test/test_workdirs.py