Metadata-Version: 1.1
Name: datary
Version: 0.1.31
Summary: Datary Python sdk lib
Home-page: https://github.com/Datary/python-sdk
Author: Datary developers team
Author-email: support@datary.io
License: UNKNOWN
Download-URL: https://github.com/Datary/python-sdk
Keywords: datary,sdk,api
Platform: UNKNOWN
Classifier: Programming Language :: Python :: 3
Classifier: Programming Language :: Python :: 3.3
Classifier: Programming Language :: Python :: 3.4
Classifier: Programming Language :: Python :: 3.5
